{
  "slug": "focus-visible-not-outline-none",
  "hints": [
    {
      "chapter": "hook",
      "junior": "outline: none on :focus removes keyboard navigation visibility for all users. It's one of the most common accessibility mistakes in real codebases.",
      "mid": ":focus-visible is the correct replacement — it shows the ring for keyboard users and hides it for mouse users. Browser support is now universal.",
      "staff": "WCAG 2.2 SC 2.4.11 is now AA — focus indicator requirements are no longer optional. Check your design system's focus ring against the contrast and size criteria."
    },
    {
      "chapter": "demo",
      "junior": "Tab through the demo in broken mode — can you tell where you are? Now try fixed mode. The ring shows exactly where keyboard focus is.",
      "mid": "Notice: in fixed mode, clicking a button doesn't show the ring. Tabbing to it does. That's :focus-visible working correctly.",
      "staff": "The fixed ring uses outline, not box-shadow. outline renders in Windows High Contrast mode; box-shadow doesn't. Always use outline for focus indicators."
    }
  ],
  "anecdotes": [
    {
      "chapter": "concept",
      "junior": "My first accessibility audit found outline: none on every interactive element — added by a designer who found the default ring ugly. :focus-visible was the clean fix.",
      "mid": "The CSS reset * { outline: none } is still in many starter templates and tutorial codebases. Always replace it with a :focus-visible rule.",
      "staff": "I've seen teams pass WCAG audits by adding outline: 2px solid transparent for keyboard users — technically visible in high contrast mode but invisible elsewhere. Don't do this."
    }
  ],
  "actions": [
    {
      "chapter": "demo",
      "junior": [
        {
          "label": "Try broken",
          "target": "[data-demo-state=broken]"
        },
        {
          "label": "Try fixed",
          "target": "[data-demo-state=fixed]"
        }
      ],
      "mid": [
        {
          "label": "Toggle broken",
          "target": "[data-demo-state=broken]"
        },
        {
          "label": "Toggle fixed",
          "target": "[data-demo-state=fixed]"
        }
      ],
      "staff": [
        {
          "label": "Broken state",
          "target": "[data-demo-state=broken]"
        },
        {
          "label": "Fixed state",
          "target": "[data-demo-state=fixed]"
        }
      ]
    },
    {
      "chapter": "hook",
      "junior": [
        {
          "label": "Jump to demo",
          "target": "[data-chapter=demo]"
        }
      ],
      "mid": [
        {
          "label": "Skip to demo",
          "target": "[data-chapter=demo]"
        }
      ],
      "staff": [
        {
          "label": "Demo chapter",
          "target": "[data-chapter=demo]"
        }
      ]
    },
    {
      "chapter": "takeaway",
      "junior": [
        {
          "label": "Back to all cases",
          "href": "/cases/"
        },
        {
          "label": "Reading library",
          "href": "/cases/library/"
        }
      ],
      "mid": [
        {
          "label": "Hub",
          "href": "/cases/"
        },
        {
          "label": "Library",
          "href": "/cases/library/"
        }
      ],
      "staff": [
        {
          "label": "Case hub",
          "href": "/cases/"
        },
        {
          "label": "War stories",
          "href": "/cases/library/"
        }
      ]
    }
  ],
  "voice": {
    "enabled": true,
    "sections": [
      {
        "chapter": "hook",
        "junior": "Hey! Today we're fixing one of the most common accessibility mistakes: removing the focus ring and making keyboard navigation invisible. The fix is one CSS rule.",
        "mid": "This case covers :focus-visible — the CSS pseudo-class that shows focus rings for keyboard users only, giving you design control without the accessibility cost.",
        "staff": "We're covering WCAG 2.2 focus appearance requirements, the :focus-visible browser heuristic, and design system token patterns for focus indicators."
      }
    ]
  }
}
